pisslink/__init__.py
pisslink/abc.py
pisslink/backoff.py
pisslink/enums.py
pisslink/errors.py
pisslink/player.py
pisslink/pool.py
pisslink/stats.py
pisslink/tracks.py
pisslink/utils.py
pisslink/websocket.py
pisslink-1.0.2.dist-info/LICENSE
pisslink-1.0.2.dist-info/METADATA
pisslink-1.0.2.dist-info/WHEEL
pisslink-1.0.2.dist-info/top_level.txt
pisslink-1.0.2.dist-info/RECORD
