Metadata-Version: 2.1
Name: pisslink
Version: 1.0.2
Summary: Minimalistic lavalink wrapper based on wavelink. Made for Pycord.
Home-page: https://github.com/BigCord-py/Pisslink
Author: KaasToast
License: MIT
Platform: UNKNOWN
License-File: LICENSE
Requires-Dist: aiohttp (<3.9.0,>=3.6.0)
